{
    "sourceFile": "resources/views/admin/student/create.blade.php",
    "activeCommit": 0,
    "commits": [
        {
            "activePatchIndex": 5,
            "patches": [
                {
                    "date": 1750559805239,
                    "content": "Index: \n===================================================================\n--- \n+++ \n"
                },
                {
                    "date": 1750559817833,
                    "content": "Index: \n===================================================================\n--- \n+++ \n@@ -45,12 +45,12 @@\n \n \n                         <div class=\"card card-primary\">\n                             <div class=\"card-header\">\n-                                <h3 class=\"card-title\">Add Fee Structure</h3>\n+                                <h3 class=\"card-title\">Add Student</h3>\n                             </div>\n \n-                            <form action=\"{{ route('fee-structure.store') }}\" method=\"post\">\n+                            <form action=\"{{ route('student.store') }}\" method=\"post\">\n                                 @csrf\n                                 <div class=\"card-body\">\n                                     <div class=\"form-group\">\n                                         <label for=\"name\">Class</label>\n"
                },
                {
                    "date": 1750559836355,
                    "content": "Index: \n===================================================================\n--- \n+++ \n@@ -72,20 +72,10 @@\n                                             @endforeach\n                                         </select>\n                                     </div>\n                                 </div>\n-                                <div class=\"card-body\">\n-                                    <div class=\"form-group\">\n-                                        <label for=\"name\">Fee Heads</label>\n-                                        <select name=\"fee_head_id\" id=\"fee_head_id\" class=\"form-control\">\n-                                            <option value=\"\">Select Fee Head</option>\n-                                            @foreach ($feeHeads as $feeHead)\n-                                                <option {{ old('fee_head_id') == $feeHead->id ? 'selected' : '' }} value=\"{{ $feeHead->id }}\">{{ $feeHead->name }}</option>\n-                                            @endforeach\n-                                        </select>\n-                                    </div>\n-                                </div>\n \n+\n                                 <div class=\"card-body\">\n                                     <div class=\"form-group\">\n                                         <label for=\"name\">April</label>\n                                         <input type=\"number\" name=\"april\" class=\"form-control\" id=\"april\"\n"
                },
                {
                    "date": 1750560128727,
                    "content": "Index: \n===================================================================\n--- \n+++ \n@@ -78,9 +78,9 @@\n                                 <div class=\"card-body\">\n                                     <div class=\"form-group\">\n                                         <label for=\"name\">April</label>\n                                         <input type=\"number\" name=\"april\" class=\"form-control\" id=\"april\"\n-                                            placeholder=\"Enter April Amount\" value=\"{{ old('april') }}\">\n+                                            placeholder=\"Enter April Amount\" value=\"{{ old('name') }}\">\n                                     </div>\n                                 </div>\n \n                                 <div class=\"card-body\">\n"
                },
                {
                    "date": 1750560138181,
                    "content": "Index: \n===================================================================\n--- \n+++ \n@@ -78,9 +78,9 @@\n                                 <div class=\"card-body\">\n                                     <div class=\"form-group\">\n                                         <label for=\"name\">April</label>\n                                         <input type=\"number\" name=\"name\" class=\"form-control\" id=\"april\"\n-                                            placeholder=\"Enter April Amount\" value=\"{{ old('name') }}\">\n+                                            placeholder=\"Enter Name\" value=\"{{ old('name') }}\">\n                                     </div>\n                                 </div>\n \n                                 <div class=\"card-body\">\n"
                },
                {
                    "date": 1750560145246,
                    "content": "Index: \n===================================================================\n--- \n+++ \n@@ -76,9 +76,9 @@\n \n \n                                 <div class=\"card-body\">\n                                     <div class=\"form-group\">\n-                                        <label for=\"name\">April</label>\n+                                        <label for=\"name\">Studen</label>\n                                         <input type=\"number\" name=\"name\" class=\"form-control\" id=\"april\"\n                                             placeholder=\"Enter Name\" value=\"{{ old('name') }}\">\n                                     </div>\n                                 </div>\n"
                }
            ],
            "date": 1750559805239,
            "name": "Commit-0",
            "content": "@extends('admin.layout')\n@section('content')\n    <div class=\"content-wrapper\">\n\n        <section class=\"content-header\">\n            <div class=\"container-fluid\">\n                <div class=\"row mb-2\">\n                    <div class=\"col-sm-12\">\n                        <h1>Fee Head</h1>\n                    </div>\n                    <div class=\"col-sm-6\">\n                        <ol class=\"breadcrumb float-sm-right\">\n                            <li class=\"breadcrumb-item\"><a href=\"{{ route('admin.dashboard') }}\">Home</a></li>\n                            <li class=\"breadcrumb-item active\">Student</li>\n                        </ol>\n                    </div>\n                </div>\n            </div>\n        </section>\n\n        <section class=\"content\">\n            <div class=\"container-fluid\">\n                <div class=\"row\">\n\n                    <div class=\"col-md-6\">\n                        @if (@Session::has('success'))\n                            <div class=\"alert alert-success\">\n                                {{ Session::get('success') }}\n                            </div>\n                        @endif\n                        @if (@Session::has('error'))\n                            <div class=\"alert alert-danger\">\n                                {{ Session::get('error') }}\n                            </div>\n                        @endif\n                        @if ($errors->any())\n                            <div class=\"alert alert-danger\">\n                                <ul>\n                                    @foreach ($errors->all() as $error)\n                                        <li>{{ $error }}</li>\n                                    @endforeach\n                                </ul>\n                            </div>\n                        @endif\n\n\n                        <div class=\"card card-primary\">\n                            <div class=\"card-header\">\n                                <h3 class=\"card-title\">Add Fee Structure</h3>\n                            </div>\n\n                            <form action=\"{{ route('fee-structure.store') }}\" method=\"post\">\n                                @csrf\n                                <div class=\"card-body\">\n                                    <div class=\"form-group\">\n                                        <label for=\"name\">Class</label>\n                                        <select name=\"class_id\" id=\"class_id\" class=\"form-control\">\n                                            <option value=\"\">Select Class</option>\n                                            @foreach ($classes as $class)\n                                                <option {{ old('class_id') == $class->id ? 'selected' : '' }} value=\"{{ $class->id }}\">{{ $class->name }}</option>\n                                            @endforeach\n                                        </select>\n                                    </div>\n                                </div>\n                                <div class=\"card-body\">\n                                    <div class=\"form-group\">\n                                        <label for=\"name\">Academic Year</label>\n                                        <select name=\"academic_year_id\" id=\"academic_year_id\" class=\"form-control\">\n                                            <option value=\"\">Select Academic Year</option>\n                                            @foreach ($academicYears as $academicYear)\n                                                <option {{ old('academic_year_id') == $academicYear->id ? 'selected' : '' }} }} value=\"{{ $academicYear->id }}\">{{ $academicYear->name }}</option>\n                                            @endforeach\n                                        </select>\n                                    </div>\n                                </div>\n                                <div class=\"card-body\">\n                                    <div class=\"form-group\">\n                                        <label for=\"name\">Fee Heads</label>\n                                        <select name=\"fee_head_id\" id=\"fee_head_id\" class=\"form-control\">\n                                            <option value=\"\">Select Fee Head</option>\n                                            @foreach ($feeHeads as $feeHead)\n                                                <option {{ old('fee_head_id') == $feeHead->id ? 'selected' : '' }} value=\"{{ $feeHead->id }}\">{{ $feeHead->name }}</option>\n                                            @endforeach\n                                        </select>\n                                    </div>\n                                </div>\n\n                                <div class=\"card-body\">\n                                    <div class=\"form-group\">\n                                        <label for=\"name\">April</label>\n                                        <input type=\"number\" name=\"april\" class=\"form-control\" id=\"april\"\n                                            placeholder=\"Enter April Amount\" value=\"{{ old('april') }}\">\n                                    </div>\n                                </div>\n\n                                <div class=\"card-body\">\n                                    <div class=\"form-group\">\n                                        <label for=\"name\">May</label>\n                                        <input type=\"number\" name=\"may\" class=\"form-control\" id=\"may\"\n                                            placeholder=\"Enter May Amount\" value=\"{{ old('may') }}\">\n                                    </div>\n                                </div>\n\n                                <div class=\"card-body\">\n                                    <div class=\"form-group\">\n                                        <label for=\"name\">June</label>\n                                        <input type=\"number\" name=\"june\" class=\"form-control\" id=\"june\"\n                                            placeholder=\"Enter June Amount\" value=\"{{ old('june') }}\">\n                                    </div>\n                                </div>\n\n                                <div class=\"card-body\">\n                                    <div class=\"form-group\">\n                                        <label for=\"name\">July</label>\n                                        <input type=\"number\" name=\"july\" class=\"form-control\" id=\"july\"\n                                            placeholder=\"Enter July Amount\" value=\"{{ old('july') }}\">\n                                    </div>\n                                </div>\n                                <div class=\"card-body\">\n                                    <div class=\"form-group\">\n                                        <label for=\"name\">August</label>\n                                        <input type=\"number\" name=\"august\" class=\"form-control\" id=\"august\"\n                                            placeholder=\"Enter August Amount\" value=\"{{ old('august') }}\">\n                                    </div>\n                                </div>\n                                <div class=\"card-body\">\n                                    <div class=\"form-group\">\n                                        <label for=\"name\">September</label>\n                                        <input type=\"number\" name=\"september\" class=\"form-control\" id=\"september\"\n                                            placeholder=\"Enter September Amount\" value=\"{{ old('september') }}\">\n                                    </div>\n                                </div>\n                                <div class=\"card-body\">\n                                    <div class=\"form-group\">\n                                        <label for=\"name\">October</label>\n                                        <input type=\"number\" name=\"october\" class=\"form-control\" id=\"october\"\n                                            placeholder=\"Enter October Amount\" value=\"{{ old('october') }}\">\n                                    </div>\n                                </div>\n                                <div class=\"card-body\">\n                                    <div class=\"form-group\">\n                                        <label for=\"name\">November</label>\n                                        <input type=\"number\" name=\"november\" class=\"form-control\" id=\"november\"\n                                            placeholder=\"Enter November Amount\" value=\"{{ old('november') }}\">\n                                    </div>\n                                </div>\n                                <div class=\"card-body\">\n                                    <div class=\"form-group\">\n                                        <label for=\"name\">December</label>\n                                        <input type=\"number\" name=\"december\" class=\"form-control\" id=\"december\"\n                                            placeholder=\"Enter December Amount\" value=\"{{ old('december') }}\">\n                                    </div>\n                                </div>\n                                <div class=\"card-body\">\n                                    <div class=\"form-group\">\n                                        <label for=\"name\">January</label>\n                                        <input type=\"number\" name=\"january\" class=\"form-control\" id=\"january\"\n                                            placeholder=\"Enter January Amount\" value=\"{{ old('january') }}\">\n                                    </div>\n                                </div>\n                                <div class=\"card-body\">\n                                    <div class=\"form-group\">\n                                        <label for=\"name\">February</label>\n                                        <input type=\"number\" name=\"february\" class=\"form-control\" id=\"february\"\n                                            placeholder=\"Enter February Amount\" value=\"{{ old('february') }}\">\n                                    </div>\n                                </div>\n                                <div class=\"card-body\">\n                                    <div class=\"form-group\">\n                                        <label for=\"name\">March</label>\n                                        <input type=\"number\" name=\"march\" class=\"form-control\" id=\"march\"\n                                            placeholder=\"Enter March Amount\" value=\"{{ old('march') }}\"\">\n                                    </div>\n                                </div>\n\n                                <div class=\"card-footer\">\n                                    <button type=\"submit\" class=\"btn btn-primary\">Submit</button>\n                                </div>\n                            </form>\n                        </div>\n\n\n\n\n                    </div>\n\n                </div>\n        </section>\n\n    </div>\n@endsection\n"
        }
    ]
}